PyGoogleBooks.py
pygooglebooks-0.1.1.dist-info/LICENSE
pygooglebooks-0.1.1.dist-info/WHEEL
pygooglebooks-0.1.1.dist-info/METADATA
pygooglebooks-0.1.1.dist-info/RECORD
