Metadata-Version: 2.1
Name: pygooglebooks
Version: 0.1.1
Summary: Python package for convenient work with Google Books service
Home-page: https://github.com/tankalxat34/PyGoogleBooks
License: MIT
Author: tankalxat34
Author-email: tankalxat34@gmail.com
Requires-Python: >=3.9,<4.0
Classifier: License :: OSI Approved :: MIT License
Classifier: Programming Language :: Python :: 3
Classifier: Programming Language :: Python :: 3.10
Classifier: Programming Language :: Python :: 3.9
Project-URL: Repository, https://github.com/tankalxat34/PyGoogleBooks
